streamlit_imp_sidebar/__init__.py
streamlit_imp_sidebar/frontend/build/asset-manifest.json
streamlit_imp_sidebar/frontend/build/bootstrap.min.css
streamlit_imp_sidebar/frontend/build/bootstrap.min.css.map
streamlit_imp_sidebar/frontend/build/imperial.png
streamlit_imp_sidebar/frontend/build/index.html
streamlit_imp_sidebar/frontend/build/sidebar.png
streamlit_imp_sidebar/frontend/build/static/css/main.3997bb57.css
streamlit_imp_sidebar/frontend/build/static/css/main.3997bb57.css.map
streamlit_imp_sidebar/frontend/build/static/css/main.fa60fd93.css
streamlit_imp_sidebar/frontend/build/static/css/main.fa60fd93.css.map
streamlit_imp_sidebar/frontend/build/static/js/main.a7563be6.js
streamlit_imp_sidebar/frontend/build/static/js/main.a7563be6.js.LICENSE.txt
streamlit_imp_sidebar/frontend/build/static/js/main.a7563be6.js.map
streamlit_imp_sidebar/frontend/build/static/js/main.cc0dab21.js
streamlit_imp_sidebar/frontend/build/static/js/main.cc0dab21.js.LICENSE.txt
streamlit_imp_sidebar/frontend/build/static/js/main.cc0dab21.js.map
streamlit_imp_sidebar-1.0.1.dist-info/LICENSE
streamlit_imp_sidebar-1.0.1.dist-info/METADATA
streamlit_imp_sidebar-1.0.1.dist-info/WHEEL
streamlit_imp_sidebar-1.0.1.dist-info/top_level.txt
streamlit_imp_sidebar-1.0.1.dist-info/RECORD
